{
	"instance" : {
		"attributePath" : " 9/26/2017 13:31:02",
		"block:" : " 9/26/2017 13:31:02",
		"attributeOrPath" : " 9/26/2017 13:31:02",
		"parent" : " 9/26/2017 13:31:02",
		"printOn:" : " 9/26/2017 13:31:02",
		"methodSections" : " 9/26/2017 13:31:02",
		"addMethodSection:" : " 9/26/2017 13:31:02",
		"block" : " 9/26/2017 13:31:02",
		"topParent" : " 9/26/2017 13:31:02",
		"versionSpec" : " 9/26/2017 13:31:02",
		"parent:" : " 9/26/2017 13:31:02",
		"versionSpec:" : " 9/26/2017 13:31:02"
	},
	"class" : { }
}