{
	"instance" : {
		"testVersion05" : "",
		"testVersion18" : "",
		"testVersion11" : "",
		"testVersion20" : "",
		"testIncrementDecrementVersionNumber" : "",
		"versionClass" : "",
		"testInvalidSpecialMatch" : "",
		"testVersion03" : "",
		"testVersion16" : "",
		"testVersion08" : "",
		"testApproxVersion02" : "",
		"testCollapseZeros" : "",
		"testVersion06" : "",
		"testVersion19" : "",
		"testVersion12" : "",
		"testVersion21" : "",
		"testVersion17" : "",
		"testSpecialMatch" : "",
		"testVersion10" : "",
		"testVersion09" : "",
		"testApproxVersion03" : "",
		"testStandardMatch" : "",
		"testVersion15" : "",
		"testVersion24" : "",
		"testVersion07" : "",
		"testApproxVersion01" : "",
		"testVersion13" : ""
	},
	"class" : { }
}