{
	"instance" : {
		"preLoad:" : "",
		"linearLoadPackageSpecs:repositories:" : "",
		"scheduleFetchFor:reference:message:" : "",
		"doLoad" : "",
		"ancestorsFor:" : "",
		"loadingSpecLoader" : "",
		"loadData" : "",
		"atomicLoadPackageSpecs:repositories:" : "",
		"explicitLoadPackageSpecs:repositories:" : "",
		"resolvePackageSpec:cachedGofer:" : "",
		"ensuredMap" : "",
		"actionLabel" : "",
		"linearLoadPackageSpec:gofer:" : "",
		"scheduleFetchFor:cachedReference:" : "",
		"ensureSpecLoader" : "",
		"loadDirective" : "",
		"cacheRepository" : "",
		"scheduleFetchFor:nearestReference:" : "",
		"postLoad:" : "",
		"printOn:" : "",
		"scheduleFetchFor:externalReference:" : "",
		"currentVersionInfoFor:" : "",
		"resolveDependencies:nearest:into:" : ""
	},
	"class" : { }
}