{
	"class" : {
		 },
	"instance" : {
		"baseline10:" : "dkh 12/30/2009 15:01",
		"baseline11:" : "DaleHenrichs 4/9/2010 11:40",
		"baselineIssue40:" : "dkh 1/12/2010 13:11",
		"baselineIssue77:" : "DaleHenrichs 12/20/2010 12:34",
		"baselineIssue95:" : "DaleHenrichs 08/30/2010 11:54",
		"baselineMoose:" : "DaleHenrichs 1/20/2010 09:59",
		"postloadExecute" : "DaleHenrichs 4/9/2010 12:31",
		"postloadSupplyingAnswers" : "dkh 1/6/2010 21:19",
		"preloadExecute" : "DaleHenrichs 4/9/2010 11:40",
		"setUp" : "DaleHenrichs 5/19/2010 14:13",
		"tearDown" : "DaleHenrichs 12/22/2010 14:11",
		"tearDownPackages:" : "DaleHenrichs 12/22/2010 14:07",
		"testBaseline11PrePostLoadFetch" : "DaleHenrichs 4/9/2010 11:42",
		"testBaseline11PrePostLoadLoad" : "DaleHenrichs 4/9/2010 13:18",
		"testBaselineFetch" : "DaleHenrichs 3/12/2010 10:34",
		"testBaselineLoad" : "dkh 01/14/2010 11:56",
		"testBaselineRecord" : "DaleHenrichs 3/12/2010 09:32",
		"testIssue40Baseline" : "DaleHenrichs 3/4/2010 20:07",
		"testIssue49PartialLoadA" : "dkh 10/11/2011 21:14",
		"testIssue49PartialLoadB" : "DaleHenrichs 01/20/2010 13:23",
		"testIssue49PartialLoadC" : "dkh 10/11/2011 21:14",
		"testIssue49PartialLoadD" : "DaleHenrichs 01/20/2010 13:57",
		"testIssue49PartialLoadE" : "DaleHenrichs 01/20/2010 13:26",
		"testIssue49PartialLoadF" : "DaleHenrichs 01/20/2010 13:55",
		"testIssue49PartialLoadG" : "dkh 10/11/2011 21:20",
		"testIssue59PackageSpecRepositoryOverrides" : "DaleHenrichs 3/7/2010 08:11",
		"testIssue77" : "DaleHenrichs 5/19/2010 14:29",
		"testIssue95" : "dkh 2/22/2011 18:36",
		"testMczFileExplicitLoad" : "DaleHenrichs 4/16/2010 10:31",
		"testMczFileImplicitLoad" : "DaleHenrichs 4/16/2010 10:31",
		"testMooseBaselineLoad" : "DaleHenrichs 2/4/2010 15:14",
		"testNestedLoad1" : "dkh 2/22/2011 18:37",
		"testNestedLoad2" : "dkh 1/5/2011 16:35",
		"testNestedLoad3" : "dkh 1/5/2011 16:35",
		"testProjectFetch" : "dkh 2/22/2011 20:07",
		"testProjectLoad" : "dkh 2/22/2011 20:07",
		"testProjectPrePostLoad" : "DaleHenrichs 4/9/2010 11:24",
		"testProjectRecord" : "dkh 9/2/2012 11:03",
		"testRepositoryOverrides" : "dkh 1/6/2010 21:19",
		"testRepositoryOverridesFetch" : "DaleHenrichs 3/12/2010 10:22",
		"testRepositoryOverridesRecord" : "DaleHenrichs 3/12/2010 10:23",
		"testSupplyingAnswerLoad" : "dkh 1/6/2010 21:20",
		"testVersionFetch" : "DaleHenrichs 3/12/2010 10:34",
		"testVersionLoad" : "dkh 1/6/2010 21:19",
		"testVersionRecord" : "DaleHenrichs 3/12/2010 10:24",
		"version10:" : "dkh 1/6/2010 20:38",
		"version11:" : "dkh 1/6/2010 20:39",
		"version30:" : "DaleHenrichs 3/11/2010 23:22",
		"version31:" : "DaleHenrichs 4/9/2010 11:40",
		"version40:" : "DaleHenrichs 3/11/2010 23:22",
		"version50:" : "DaleHenrichs 3/11/2010 23:23",
		"version60:" : "DaleHenrichs 4/16/2010 11:12",
		"version61:" : "DaleHenrichs 4/16/2010 11:12",
		"version62:" : "DaleHenrichs 4/16/2010 10:26",
		"version63:" : "DaleHenrichs 4/16/2010 10:26" } }
